datasette_mp3_audio/__init__.py
datasette_mp3_audio/static/datasette-mp3-audio.js
datasette_mp3_audio-0.2.dist-info/LICENSE
datasette_mp3_audio-0.2.dist-info/METADATA
datasette_mp3_audio-0.2.dist-info/WHEEL
datasette_mp3_audio-0.2.dist-info/entry_points.txt
datasette_mp3_audio-0.2.dist-info/top_level.txt
datasette_mp3_audio-0.2.dist-info/RECORD
