Metadata-Version: 2.1
Name: datasette-mp3-audio
Version: 0.2
Summary: Turn .mp3 URLs into an audio player in the Datasette interface
Home-page: https://github.com/simonw/datasette-mp3-audio
Author: Simon Willison
License: Apache License, Version 2.0
Project-URL: Issues, https://github.com/simonw/datasette-mp3-audio/issues
Project-URL: CI, https://github.com/simonw/datasette-mp3-audio/actions
Project-URL: Changelog, https://github.com/simonw/datasette-mp3-audio/releases
Classifier: Framework :: Datasette
Classifier: License :: OSI Approved :: Apache Software License
Requires-Python: >=3.7
License-File: LICENSE
Requires-Dist: datasette
Provides-Extra: test
Requires-Dist: pytest ; extra == 'test'
Requires-Dist: pytest-asyncio ; extra == 'test'
Requires-Dist: sqlite-utils ; extra == 'test'
